enveloop_py/__init__.py
enveloop_py/api.py
enveloop_py/client.py
enveloop_py/message.py
enveloop_py/message_response.py
enveloop_py/template.py
enveloop_py/template_response.py
enveloop_py-0.2.0.dist-info/METADATA
enveloop_py-0.2.0.dist-info/WHEEL
enveloop_py-0.2.0.dist-info/licenses/LICENSE
enveloop_py-0.2.0.dist-info/RECORD
