Metadata-Version: 2.3
Name: enveloop-py
Version: 0.2.0
Summary: Enveloop API SDK
Project-URL: Homepage, https://github.com/enveloophq/enveloop-py
Project-URL: Bug Tracker, https://github.com/enveloophq/enveloop-py/issues
Author-email: Ben Wyrosdick <ben.wyrosdick@gmail.com>
License-File: LICENSE
Classifier: License :: OSI Approved :: MIT License
Classifier: Operating System :: OS Independent
Classifier: Programming Language :: Python :: 3
Requires-Python: >=3.7
